{
	"node": "extremeScenarios",
	"nodeVersion": "1.0",
	"codexVersion": "1.0",
	"icon": "wiro.svg",
	"description": "Turn your selfies into blockbusters! This AI tool takes your image and places it into dramatic,",
	"categories": [
		"AI",
		"Editing",
		"Image"
	],
	"alias": [
		"Wiro",
		"WiroAI",
		"Extreme Scenarios"
	],
	"resources": {
		"primaryDocumentation": [
			{
				"url": "https://wiro.ai/models/wiro/extreme-scenarios#apisamples-curl"
			}
		],
		"credentialDocumentation": [
			{
				"url": "https://wiro.ai/docs/authentication"
			}
		]
	}
}