{
	"node": "animateDiff",
	"nodeVersion": "1.0",
	"codexVersion": "1.0",
	"icon": "wiro.svg",
	"description": "It generates a video from the given prompt",
	"categories": [
		"AI",
		"Video"
	],
	"alias": [
		"Wiro",
		"WiroAI",
		"AnimateDiff Text To Video",
		"Animate Diff"
	],
	"resources": {
		"primaryDocumentation": [
			{
				"url": "https://wiro.ai/models/wiro/animate-diff#apisamples-curl"
			}
		],
		"credentialDocumentation": [
			{
				"url": "https://wiro.ai/docs/authentication"
			}
		]
	}
}