{
	"node": "glmImage",
	"nodeVersion": "1.0",
	"codexVersion": "1.0",
	"icon": "wiro.svg",
	"description": "Access GLM Image API by ZAI on Wiro. Simple integration, transparent pricing, and comprehensive",
	"categories": [
		"AI",
		"Editing",
		"Image"
	],
	"alias": [
		"Wiro",
		"WiroAI",
		"Zai Org",
		"Glm Image"
	],
	"resources": {
		"primaryDocumentation": [
			{
				"url": "https://wiro.ai/models/zai-org/glm-image#apisamples-curl"
			}
		],
		"credentialDocumentation": [
			{
				"url": "https://wiro.ai/docs"
			}
		]
	}
}